README.md
setup.py
greece_utils.egg-info/PKG-INFO
greece_utils.egg-info/SOURCES.txt
greece_utils.egg-info/dependency_links.txt
greece_utils.egg-info/not-zip-safe
greece_utils.egg-info/requires.txt
greece_utils.egg-info/top_level.txt
utils/__init__.py
utils/check/__init__.py
utils/check/descriptor.py
utils/check/type.py
utils/check/value.py
utils/sys/__init__.py
utils/sys/browser.py
utils/sys/const.py
utils/sys/io.py
utils/sys/reader.py
utils/sys/timer.py
utils/toolset/__init__.py
utils/toolset/list.py
utils/toolset/sqlcsv.py