Metadata-Version: 2.1
Name: greece-utils
Version: 0.2
Summary: GREECE utils
Home-page: http://github.com/benjamin-pillot/greece-utils
Author: Benjamin Pillot
Author-email: benjaminpillot@riseup.net
License: GNU GPL v3.0
Platform: UNKNOWN
